cortexflow/__init__.py
cortexflow/cortexflow.py
cortexflow-1.0.8.dist-info/METADATA
cortexflow-1.0.8.dist-info/WHEEL
cortexflow-1.0.8.dist-info/top_level.txt
cortexflow-1.0.8.dist-info/RECORD
