Metadata-Version: 2.1
Name: cortexflow
Version: 1.0.8
Summary: A Machine learning library
Home-page: UNKNOWN
Author: sidharth
Author-email: sidharthss2690@gmail.com
License: UNKNOWN
Platform: UNKNOWN
Classifier: Programming Language :: Python :: 3
Classifier: License :: OSI Approved :: MIT License
Classifier: Operating System :: OS Independent
Requires-Python: >=3.6
Requires-Dist: matplotlib
Requires-Dist: numpy
Requires-Dist: pandas
Requires-Dist: scikit-learn
Requires-Dist: scipy
Requires-Dist: tensorflow
